prometheuspvesd/__init__.py
prometheuspvesd/cli.py
prometheuspvesd/client.py
prometheuspvesd/config.py
prometheuspvesd/discovery.py
prometheuspvesd/exception.py
prometheuspvesd/logger.py
prometheuspvesd/model.py
prometheuspvesd/test/__init__.py
prometheuspvesd/test/data/config.yaml
prometheuspvesd/test/fixtures/__init__.py
prometheuspvesd/test/fixtures/fixtures.py
prometheuspvesd/test/unit/conftest.py
prometheuspvesd/test/unit/test_cli.py
prometheuspvesd/test/unit/test_config.py
prometheuspvesd/test/unit/test_discovery.py
prometheuspvesd/test/unit/test_model.py
prometheuspvesd/test/unit/test_types.py
prometheuspvesd/utils.py
prometheus_pve_sd-5.1.3.dist-info/METADATA
prometheus_pve_sd-5.1.3.dist-info/WHEEL
prometheus_pve_sd-5.1.3.dist-info/entry_points.txt
prometheus_pve_sd-5.1.3.dist-info/licenses/LICENSE
prometheus_pve_sd-5.1.3.dist-info/RECORD
