Metadata-Version: 2.4
Name: prometheus-pve-sd
Version: 5.1.3
Summary: Prometheus Service Discovery for Proxmox VE.
License: MIT
License-File: LICENSE
Keywords: prometheus,sd,pve,metrics
Author: Robert Kaussow
Author-email: mail@thegeeklab.de
Requires-Python: >=3.11.0,<4.0.0
Classifier: Development Status :: 5 - Production/Stable
Classifier: Environment :: Console
Classifier: Intended Audience :: Developers
Classifier: Intended Audience :: Information Technology
Classifier: Intended Audience :: System Administrators
Classifier: License :: OSI Approved :: MIT License
Classifier: Natural Language :: English
Classifier: Operating System :: POSIX
Classifier: Programming Language :: Python :: 3
Classifier: Programming Language :: Python :: 3.11
Classifier: Programming Language :: Python :: 3.12
Classifier: Programming Language :: Python :: 3.13
Classifier: Programming Language :: Python :: 3.14
Classifier: Topic :: Utilities
Requires-Dist: anyconfig (==0.14.0)
Requires-Dist: appdirs (==1.4.4)
Requires-Dist: colorama (==0.4.6)
Requires-Dist: environs (==14.5.0)
Requires-Dist: jsonschema (==4.26.0)
Requires-Dist: nested-lookup (==0.2.25)
Requires-Dist: prometheus-client (==0.24.0)
Requires-Dist: proxmoxer (==2.2.0)
Requires-Dist: python-json-logger (==4.0.0)
Requires-Dist: requests (==2.32.5)
Requires-Dist: ruamel.yaml (==0.19.1)
Project-URL: Documentation, https://github.com/thegeeklab/prometheus-pve-sd/
Project-URL: Homepage, https://github.com/thegeeklab/prometheus-pve-sd/
Project-URL: Repository, https://github.com/thegeeklab/prometheus-pve-sd/
